{
  "camera_setting":{
    "look_at":[25,25,60,25,25,0],
    "projection_matrix":[800, 600, 500, 500, 400, 300, 0.1, 100]
  },
  "simulator": {
    "platform":{
      "color":[0.0, 1.0, 0.0],
      "size":2.0
    },
    "landmark": {
      "color":[0.8, 0.2, 0.0],
      "size":0.5
    },
    "waypoint":{
      "color":[0.8, 0.3, 0.0],
      "size": 0.5
    }
  },
  "slam_system": {
    "platform":{
      "color":[0.3, 0.3, 0.7],
      "size":2.0
    },
    "landmark": {
      "color":[0.0, 0.5, 1.0],
      "size":0.5
    },
    "measurment":{
      "gps_color":[0.1,0.6,0.3],
      "lm_range_bearing_color":[0.6,0.6,0.0],
      "lm_observation_color":[0.3,0.7,0.0]
    },
    "marginal_update_period":100
  },
  "frame_pause":10000
}
